numpyasciiart/README.MD
numpyasciiart/__init__.py
numpyasciiart/requirements.txt
numpyasciiart/thirdparty.json
numpyasciiart-0.10.dist-info/LICENSE.rst
numpyasciiart-0.10.dist-info/METADATA
numpyasciiart-0.10.dist-info/WHEEL
numpyasciiart-0.10.dist-info/top_level.txt
numpyasciiart-0.10.dist-info/RECORD
