Metadata-Version: 2.1
Name: numpyasciiart
Version: 0.10
Summary: Converts an image to ASCII art using numpy / numexpr / cv2
Home-page: https://github.com/hansalemaos/numpyasciiart
Author: Johannes Fischer
Author-email: aulasparticularesdealemaosp@gmail.com
License: MIT
Keywords: count,colours,colors,rgb,numpy
Classifier: Development Status :: 4 - Beta
Classifier: Programming Language :: Python :: 3 :: Only
Classifier: Programming Language :: Python :: 3.10
Classifier: Topic :: Software Development :: Libraries :: Python Modules
Classifier: Topic :: Utilities
License-File: LICENSE.rst
Requires-Dist: a-cv-imwrite-imread-plus
Requires-Dist: numexpr
Requires-Dist: numpy
Requires-Dist: opencv-python
